pyresolvers/__init__.py
pyresolvers/__main__.py
pyresolvers/validator.py
pyresolvers/lib/__init__.py
pyresolvers/lib/core/__init__.py
pyresolvers/lib/core/__version__.py
pyresolvers/lib/core/input.py
pyresolvers/lib/core/output.py
pyresolvers-2.4.3.dist-info/METADATA
pyresolvers-2.4.3.dist-info/WHEEL
pyresolvers-2.4.3.dist-info/entry_points.txt
pyresolvers-2.4.3.dist-info/top_level.txt
pyresolvers-2.4.3.dist-info/RECORD
