Metadata-Version: 2.4
Name: pyresolvers
Version: 2.4.3
Summary: High-performance async DNS resolver validation and speed testing library
Home-page: https://github.com/PigeonSec/pyresolvers
Author: Karl
Author-email: 
License: GPL-3.0
Project-URL: Homepage, https://github.com/PigeonSec/pyresolvers
Project-URL: Documentation, https://github.com/PigeonSec/pyresolvers#readme
Project-URL: Repository, https://github.com/PigeonSec/pyresolvers
Project-URL: Bug Tracker, https://github.com/PigeonSec/pyresolvers/issues
Keywords: dns,resolver,validation,speed-test,async,networking
Classifier: Development Status :: 4 - Beta
Classifier: Intended Audience :: Developers
Classifier: Intended Audience :: System Administrators
Classifier: License :: OSI Approved :: GNU General Public License v3 (GPLv3)
Classifier: Programming Language :: Python :: 3
Classifier: Programming Language :: Python :: 3.8
Classifier: Programming Language :: Python :: 3.9
Classifier: Programming Language :: Python :: 3.10
Classifier: Programming Language :: Python :: 3.11
Classifier: Programming Language :: Python :: 3.12
Classifier: Programming Language :: Python :: 3.13
Classifier: Programming Language :: Python :: 3.14
Classifier: Topic :: Internet :: Name Service (DNS)
Classifier: Topic :: System :: Networking
Requires-Python: >=3.12
Requires-Dist: dnspython>=2.0.0
Requires-Dist: colorclass>=2.2.2
Dynamic: home-page
Dynamic: requires-python
